fixthaipdf/__init__.py
fixthaipdf/core.py
fixthaipdf/dict.py
fixthaipdf/more_dict.py
tests/__init__.py
tests/test_clean.py
FixThaiPDF-0.2.1.dist-info/LICENSE
FixThaiPDF-0.2.1.dist-info/METADATA
FixThaiPDF-0.2.1.dist-info/WHEEL
FixThaiPDF-0.2.1.dist-info/top_level.txt
FixThaiPDF-0.2.1.dist-info/RECORD
